graphomotor/__init__.py
graphomotor/__main__.py
graphomotor/core/__init__.py
graphomotor/core/cli.py
graphomotor/core/config.py
graphomotor/core/models.py
graphomotor/core/orchestrator.py
graphomotor/features/__init__.py
graphomotor/features/distance.py
graphomotor/features/drawing_error.py
graphomotor/features/time.py
graphomotor/features/velocity.py
graphomotor/io/__init__.py
graphomotor/io/reader.py
graphomotor/plot/__init__.py
graphomotor/plot/feature_plots.py
graphomotor/plot/spiral_plots.py
graphomotor/utils/__init__.py
graphomotor/utils/center_spiral.py
graphomotor/utils/generate_reference_spiral.py
graphomotor/utils/plotting.py
graphomotor-0.2.0.dist-info/METADATA
graphomotor-0.2.0.dist-info/WHEEL
graphomotor-0.2.0.dist-info/entry_points.txt
graphomotor-0.2.0.dist-info/licenses/LICENSE
graphomotor-0.2.0.dist-info/RECORD
