Metadata-Version: 2.4
Name: graphomotor
Version: 0.2.0
Summary: A Python toolkit for analysis of graphomotor data collected via Curious
Author-email: Alp Erkent <alp.erkent@childmind.org>, Adam Santorelli <adam.santorelli@childmind.org>
License-Expression: LGPL-2.1
License-File: LICENSE
Requires-Python: >=3.11
Requires-Dist: matplotlib>=3.10.0
Requires-Dist: pandas>=2.2.3
Requires-Dist: pydantic>=2.11.1
Requires-Dist: scipy>=1.15.2
Requires-Dist: seaborn>=0.13.0
Requires-Dist: shapely>=2.1.0
Requires-Dist: tqdm>=4.66.0
Requires-Dist: typer>=0.12.0
